xxl_admin/__init__.py
xxl_admin/client.py
xxl_admin/commands.py
xxl_admin/completers.py
xxl_admin/context.py
xxl_admin/core.py
xxl_admin/key_bindings.py
xxl_admin/settings.py
xxl_admin/utils.py
xxl_admin/xxl.py
xxl_admin_sh-0.1.1.dist-info/METADATA
xxl_admin_sh-0.1.1.dist-info/WHEEL
xxl_admin_sh-0.1.1.dist-info/entry_points.txt
xxl_admin_sh-0.1.1.dist-info/licenses/LICENSE
xxl_admin_sh-0.1.1.dist-info/RECORD
