Metadata-Version: 2.1
Name: xxl-admin-sh
Version: 0.1.1
Summary: A shell utility for XXL-Admin
Author-Email: tanglh <tlhk2@163.com>
License: MIT
Requires-Python: >=3.9
Requires-Dist: httpx>=0.25.0
Requires-Dist: typer>=0.9.0
Requires-Dist: pydantic>=2.4.2
Requires-Dist: prompt-toolkit>=3.0.39
Requires-Dist: rich>=13.6.0
Requires-Dist: arrow>=1.3.0
